lab_1/bound_flasher.v
module bound_flasher(clk, flick, reset, lamp);

input wire clk;
input wire flick;
input wire reset;

output reg [15:0] lamp;

localparam s0 = 4'b0000;
localparam s1 = 4'b0001;
localparam s2 = 4'b0010;
localparam s3 = 4'b0011;
localparam s4 = 4'b0100;    
localparam s5 = 4'b0101;
localparam s6 = 4'b0110;
localparam s7 = 4'b0111;
localparam s8 = 4'b1000;
localparam s9 = 4'b1001;
localparam s10 = 4'b1010;

reg [3:0] state = 0;
reg [4:0] bit_shifted = 0;
reg [4:0] n_bit_shift = 0;

always @(posedge reset) begin
    state <= s0;
    bit_shifted <= 0;
    n_bit_shift <= 0;
    lamp <= 0;
end

always @(posedge clk) begin
    // state 0
    if (state == s0) begin
        if (bit_shifted < n_bit_shift)begin
            lamp = lamp >> 1;
            bit_shifted = bit_shifted + 1;
        end
        else if (flick) begin
            state <= s1;
            bit_shifted <= 0;
            n_bit_shift <= 5;
        end else begin
            state <= s0;
        end
    end
    // state 1
    else if (state == s1) begin
        if (bit_shifted <= n_bit_shift)begin
            lamp <= (lamp << 1) + 1;
            bit_shifted <= bit_shifted + 1;
        end else begin
            state <= s2;
            bit_shifted = 0;
            n_bit_shift = 5;
        end
    end
    // state 2
    else if (state == s2) begin
        if (bit_shifted <= n_bit_shift)begin
            lamp = lamp >> 1;
            bit_shifted = bit_shifted + 1;
        end else begin
            state = s10;
            bit_shifted = 0;
            n_bit_shift = 5;
        end
    end
    // state 3
    else if (state == s3) begin
        if (bit_shifted <= n_bit_shift)begin
            lamp = (lamp << 1) + 1;
            bit_shifted = bit_shifted + 1;
        end else begin
            state = flick ? s4 : s5;
            bit_shifted = 0;
            n_bit_shift = (state == s4) ? 10 : 5;
        end
    end
    // state 4
    else if (state == s4) begin
        if (bit_shifted <= n_bit_shift)begin
            lamp = lamp >> 1;
            bit_shifted = bit_shifted + 1;
        end else begin
            state = s4;
        end
    end
    // state 5
    else if (state == s5) begin
        if (bit_shifted <= n_bit_shift) begin
            lamp = lamp >> 1;
            bit_shifted = bit_shifted + 1;
        end else begin
            state = s6;
            bit_shifted = 0;
            n_bit_shift = 0;
        end
    end
    // state 6
    else if (state == s6) begin
        if (bit_shifted <= n_bit_shift) begin
            lamp = (lamp << 1) + 1;
            bit_shifted = bit_shifted + 1;
        end else begin
            state = flick ? s7 : s9;
            bit_shifted = 0;
            n_bit_shift = (state == s7) ? 1 : 4;
        end
    end
    // state 7
    else if (state == s7) begin
        if (bit_shifted <= n_bit_shift) begin
            lamp = lamp >> 1;
            bit_shifted = bit_shifted + 1;
        end else begin
            state = 6;
            bit_shifted = 0;
            n_bit_shift = 1;
        end
    end
    // state 8
    else if (state == s8) begin
        if (bit_shifted <= n_bit_shift) begin
            lamp = (lamp << 1) + 1;
            bit_shifted = bit_shifted + 1;
        end else begin
            state <= s0;
            bit_shifted <= 0;
            n_bit_shift <= 16;
        end
    end
    // state 9
    else if (state == s9) begin
        if (bit_shifted <= n_bit_shift) begin
            lamp = (lamp << 1) + 1;
            bit_shifted = bit_shifted + 1;
        end else begin
            state = flick ? s5 : s8;
            bit_shifted = 0;
            n_bit_shift = 5;
        end
    end
    // state 10
    else if (state == s10) begin
        if (bit_shifted <= n_bit_shift) begin
            lamp = (lamp << 1) + 1;
            bit_shifted = bit_shifted + 1;
        end else begin
            state = flick ? s2 : s3;
            bit_shifted = 0;
            n_bit_shift = (state == s3) ? 4 : 5;
        end
    end
end

endmodule

lab_1/tb.v
module bound_flasher_tb;
    reg clk;
    reg flick;
    reg reset;
    wire [15:0] lamp;

    bound_flasher uut
    (
        .clk (clk),
        .flick (flick),
        .reset(reset),
        .lamp (lamp)
    );

    initial begin
        $dumpfile("bound_flash_tb.vcd");
        $dumpvars(0, bound_flasher_tb);
    end

    initial begin
        clk = 0;
        reset = 1;
    end

    always #10 clk = ~clk;

    initial begin
        #10 
        reset = 0;
        #10
        assign flick = 1;
        #10
        repeat(5) @ (clk);
        #10
        assign flick = 0;
        #10
        repeat(90) @ (clk);
        #10
        assign flick = 0;
        #10
        repeat(90) @ (clk);
        #10
        assign flick = 1;
        #10
        repeat(90) @ (clk);
        $finish;
    end
endmodule

lab_1/bound_flash_tb.vcd
$date
	Sat Feb 18 21:05:07 2023
$end
$version
	Icarus Verilog
$end
$timescale
	1s
$end
$scope module bound_flasher_tb $end
$var wire 16 ! lamp [15:0] $end
$var reg 1 " clk $end
$var reg 1 # flick $end
$var reg 1 $ reset $end
$scope module uut $end
$var wire 1 " clk $end
$var wire 1 # flick $end
$var wire 1 $ reset $end
$var parameter 4 % s0 $end
$var parameter 4 & s1 $end
$var parameter 4 ' s10 $end
$var parameter 4 ( s2 $end
$var parameter 4 ) s3 $end
$var parameter 4 * s4 $end
$var parameter 4 + s5 $end
$var parameter 4 , s6 $end
$var parameter 4 - s7 $end
$var parameter 4 . s8 $end
$var parameter 4 / s9 $end
$var reg 5 0 bit_shifted [4:0] $end
$var reg 16 1 lamp [15:0] $end
$var reg 5 2 n_bit_shift [4:0] $end
$var reg 4 3 state [3:0] $end
$upscope $end
$upscope $end
$enddefinitions $end
$comment Show the parameter values. $end
$dumpall
b1001 /
b1000 .
b111 -
b110 ,
b101 +
b100 *
b11 )
b10 (
b1010 '
b1 &
b0 %
$end
#0
$dumpvars
b0 3
b0 2
b0 1
b0 0
1$
x#
0"
b0 !
$end
#10
0$
1"
#20
1#
0"
#30
b101 2
b1 3
1"
#40
0"
#50
b1 0
b1 !
b1 1
1"
#60
0"
#70
b10 0
b11 !
b11 1
1"
#80
0"
#90
b11 0
b111 !
b111 1
0#
1"
#100
0"
#110
b100 0
b1111 !
b1111 1
1"
#120
0"
#130
b101 0
b11111 !
b11111 1
1"
#140
0"
#150
b110 0
b111111 !
b111111 1
1"
#160
0"
#170
b10 3
b0 0
1"
#180
0"
#190
b1 0
b11111 !
b11111 1
1"
#200
0"
#210
b10 0
b1111 !
b1111 1
1"
#220
0"
#230
b11 0
b111 !
b111 1
1"
#240
0"
#250
b100 0
b11 !
b11 1
1"
#260
0"
#270
b101 0
b1 !
b1 1
1"
#280
0"
#290
b110 0
b0 !
b0 1
1"
#300
0"
#310
b0 0
b1010 3
1"
#320
0"
#330
b1 0
b1 !
b1 1
1"
#340
0"
#350
b10 0
b11 !
b11 1
1"
#360
0"
#370
b11 0
b111 !
b111 1
1"
#380
0"
#390
b100 0
b1111 !
b1111 1
1"
#400
0"
#410
b101 0
b11111 !
b11111 1
1"
#420
0"
#430
b110 0
b111111 !
b111111 1
1"
#440
0"
#450
b100 2
b0 0
b11 3
1"
#460
0"
#470
b1 0
b1111111 !
b1111111 1
1"
#480
0"
#490
b10 0
b11111111 !
b11111111 1
1"
#500
0"
#510
b11 0
b111111111 !
b111111111 1
1"
#520
0"
#530
b100 0
b1111111111 !
b1111111111 1
1"
#540
0"
#550
b101 0
b11111111111 !
b11111111111 1
1"
#560
0"
#570
b101 2
b0 0
b101 3
1"
#580
0"
#590
b1 0
b1111111111 !
b1111111111 1
1"
#600
0"
#610
b10 0
b111111111 !
b111111111 1
1"
#620
0"
#630
b11 0
b11111111 !
b11111111 1
1"
#640
0"
#650
b100 0
b1111111 !
b1111111 1
1"
#660
0"
#670
b101 0
b111111 !
b111111 1
1"
#680
0"
#690
b110 0
b11111 !
b11111 1
1"
#700
0"
#710
b0 2
b0 0
b110 3
1"
#720
0"
#730
b1 0
b111111 !
b111111 1
1"
#740
0"
#750
b100 2
b0 0
b1001 3
1"
#760
0"
#770
b1 0
b1111111 !
b1111111 1
1"
#780
0"
#790
b10 0
b11111111 !
b11111111 1
1"
#800
0"
#810
b11 0
b111111111 !
b111111111 1
1"
#820
0"
#830
b100 0
b1111111111 !
b1111111111 1
1"
#840
0"
#850
b101 0
b11111111111 !
b11111111111 1
1"
#860
0"
#870
b101 2
b0 0
b1000 3
1"
#880
0"
#890
b1 0
b111111111111 !
b111111111111 1
1"
#900
0"
#910
b10 0
b1111111111111 !
b1111111111111 1
1"
#920
0"
#930
b11 0
b11111111111111 !
b11111111111111 1
1"
#940
0"
#950
b100 0
b111111111111111 !
b111111111111111 1
1"
#960
0"
#970
b101 0
b1111111111111111 !
b1111111111111111 1
1"
#980
0"
#990
b110 0
1"
#1000
0"
#1010
b10000 2
b0 0
b0 3
1"
#1020
0"
#1030
b1 0
b111111111111111 !
b111111111111111 1
1"
#1040
0"
#1050
b10 0
b11111111111111 !
b11111111111111 1
1"
#1060
0"
#1070
b11 0
b1111111111111 !
b1111111111111 1
1"
#1080
0"
#1090
b100 0
b111111111111 !
b111111111111 1
1"
#1100
0"
#1110
b101 0
b11111111111 !
b11111111111 1
1"
#1120
0"
#1130
b110 0
b1111111111 !
b1111111111 1
1"
#1140
0"
#1150
b111 0
b111111111 !
b111111111 1
1"
#1160
0"
#1170
b1000 0
b11111111 !
b11111111 1
1"
#1180
0"
#1190
b1001 0
b1111111 !
b1111111 1
1"
#1200
0"
#1210
b1010 0
b111111 !
b111111 1
1"
#1220
0"
#1230
b1011 0
b11111 !
b11111 1
1"
#1240
0"
#1250
b1100 0
b1111 !
b1111 1
1"
#1260
0"
#1270
b1101 0
b111 !
b111 1
1"
#1280
0"
#1290
b1110 0
b11 !
b11 1
1"
#1300
0"
#1310
b1111 0
b1 !
b1 1
1"
#1320
0"
#1330
b10000 0
b0 !
b0 1
1"
