lab_1/bound_flasher.v
module bound_flasher(clk, flick, reset, lamp);

input wire clk;
input wire flick;
input wire reset;

output reg [15:0] lamp;

localparam s0 = 4'b0000;
localparam s1 = 4'b0001;
localparam s2 = 4'b0010;
localparam s3 = 4'b0011;
localparam s4 = 4'b0100;    
localparam s5 = 4'b0101;
localparam s6 = 4'b0110;
localparam s7 = 4'b0111;
localparam s8 = 4'b1000;
localparam s9 = 4'b1001;
localparam s10 = 4'b1010;

reg [3:0] state = 0;
reg [4:0] bit_shifted = 0;
reg [4:0] n_bit_shift = 0;

always @(posedge reset) begin
    state <= s0;
    bit_shifted <= 0;
    n_bit_shift <= 0;
    lamp <= 0;
end

always @(posedge clk) begin
    // state 0
    if (state == s0) begin
        if (bit_shifted < n_bit_shift)begin
            lamp = lamp >> 1;
            bit_shifted = bit_shifted + 1;
        end
        else if (flick) begin
            state = s1;
            bit_shifted = 0;
            n_bit_shift = 4;
            lamp = (lamp << 1) + 1;
        end else begin
            state = s0;
        end
    end
    // state 1
    else if (state == s1) begin
        if (bit_shifted <= n_bit_shift)begin
            lamp = (lamp << 1) + 1;
            bit_shifted = bit_shifted + 1;
        end else begin
            state = s2;
            bit_shifted = 0;
            n_bit_shift = 4;
            lamp = lamp >> 1;
        end
    end
    // state 2
    else if (state == s2) begin
        if (bit_shifted <= n_bit_shift)begin
            lamp = lamp >> 1;
            bit_shifted = bit_shifted + 1;
        end else begin
            state = s10;
            bit_shifted = 0;
            n_bit_shift = 4;
            lamp = (lamp << 1) + 1;
        end
    end
    // state 3
    else if (state == s3) begin
        if (bit_shifted <= n_bit_shift)begin
            lamp = (lamp << 1) + 1;
            bit_shifted = bit_shifted + 1;
        end else begin
            state = flick ? s4 : s5;
            bit_shifted = 0;
            n_bit_shift = (state == s4) ? 9 : 4;
            lamp = lamp >> 1;
        end
    end
    // state 4
    else if (state == s4) begin
        if (bit_shifted <= n_bit_shift)begin
            lamp = lamp >> 1;
            bit_shifted = bit_shifted + 1;
        end else begin
            state = s4;
        end
    end
    // state 5
    else if (state == s5) begin
        if (bit_shifted <= n_bit_shift) begin
            lamp = lamp >> 1;
            bit_shifted = bit_shifted + 1;
        end else begin
            state = s6;
            bit_shifted = 0;
            n_bit_shift = 0;
            lamp = (lamp << 1) + 1;
        end
    end
    // state 6
    else if (state == s6) begin
        if (bit_shifted <= n_bit_shift) begin
            lamp = (lamp << 1) + 1;
            bit_shifted = bit_shifted + 1;
        end else begin
            state = flick ? s7 : s9;
            bit_shifted = 0;
            n_bit_shift = (state == s7) ? 0 : 3;
            lamp = (state == s7) ? lamp >> 1 : (lamp << 1) + 1;
        end
    end
    // state 7
    else if (state == s7) begin
        if (bit_shifted <= n_bit_shift) begin
            lamp = lamp >> 1;
            bit_shifted = bit_shifted + 1;
        end else begin
            state = 6;
            bit_shifted = 0;
            n_bit_shift = 1;
        end
    end
    // state 8
    else if (state == s8) begin
        if (bit_shifted <= n_bit_shift) begin
            lamp = (lamp << 1) + 1;
            bit_shifted = bit_shifted + 1;
        end else begin
            state = s0;
            bit_shifted = 0;
            n_bit_shift = 15;
            lamp = lamp >> 1;
        end
    end
    // state 9
    else if (state == s9) begin
        if (bit_shifted <= n_bit_shift) begin
            lamp = (lamp << 1) + 1;
            bit_shifted = bit_shifted + 1;
        end else begin
            state = flick ? s5 : s8;
            bit_shifted = 0;
            n_bit_shift = (state == s8) ? 2 : 4;
            lamp = (state == s5) ? lamp >> 1 : (lamp << 1) + 1;
        end
    end
    // state 10
    else if (state == s10) begin
        if (bit_shifted <= n_bit_shift) begin
            lamp = (lamp << 1) + 1;
            bit_shifted = bit_shifted + 1;
        end else begin
            state = flick ? s2 : s3;
            bit_shifted = 0;
            n_bit_shift = (state == s3) ? 3 : 4;
            lamp = (state == s2) ? lamp >> 1 : (lamp << 1) + 1;
        end
    end
end

endmodule

lab_1/tb.v
module bound_flasher_tb;
    reg clk;
    reg flick;
    reg reset;
    wire [15:0] lamp;

    bound_flasher uut
    (
        .clk (clk),
        .flick (flick),
        .reset(reset),
        .lamp (lamp)
    );

    initial begin
        $dumpfile("bound_flash_tb.vcd");
        $dumpvars(0, bound_flasher_tb);
    end

    always #5 clk = ~clk;

    initial begin
        
    end

    initial begin
        clk = 0;
        flick = 0;
        reset = 1;
        #100 flick = 1'b1;
        #50 flick = 1'b0;
        #450 flick = 1'b1;
        #400 flick = 1'b0;
        #50 flick = 1'b1;
        #250 flick = 1'b0;
        #100 flick = 1'b1;
        #100 flick = 1'b0;
        #100 flick = 1'b1;
        #100 flick = 1'b0;
        #200 flick = 1'b1;
        #100 flick = 1'b0;
        #50 flick = 1'b1;
        #100 flick = 1'b0;
        #300 
        assign flick = 1;
        #10
        repeat(5) @ (clk);
        #10
        assign flick = 0;
        #10
        repeat(70) @ (clk);
        #10
        assign flick = 1;
        #10
        repeat(90) @ (clk);
        #10
        assign flick = 0;
        #10
        assign flick = 0;
        #10
        repeat(90) @ (clk);
        #10
        assign flick = 1;
        #10
        repeat(90) @ (clk);
        $finish;
    end
endmodule

lab_1/bound_flash_tb.vcd
$date
	Sun Feb 19 14:18:47 2023
$end
$version
	Icarus Verilog
$end
$timescale
	1s
$end
$scope module bound_flasher_tb $end
$var wire 16 ! lamp [15:0] $end
$var reg 1 " clk $end
$var reg 1 # flick $end
$var reg 1 $ reset $end
$scope module uut $end
$var wire 1 " clk $end
$var wire 1 # flick $end
$var wire 1 $ reset $end
$var parameter 4 % s0 $end
$var parameter 4 & s1 $end
$var parameter 4 ' s10 $end
$var parameter 4 ( s2 $end
$var parameter 4 ) s3 $end
$var parameter 4 * s4 $end
$var parameter 4 + s5 $end
$var parameter 4 , s6 $end
$var parameter 4 - s7 $end
$var parameter 4 . s8 $end
$var parameter 4 / s9 $end
$var reg 5 0 bit_shifted [4:0] $end
$var reg 16 1 lamp [15:0] $end
$var reg 5 2 n_bit_shift [4:0] $end
$var reg 4 3 state [3:0] $end
$upscope $end
$upscope $end
$enddefinitions $end
$comment Show the parameter values. $end
$dumpall
b1001 /
b1000 .
b111 -
b110 ,
b101 +
b100 *
b11 )
b10 (
b1010 '
b1 &
b0 %
$end
#0
$dumpvars
b0 3
b0 2
b0 1
b0 0
1$
0#
0"
b0 !
$end
#5
1"
#10
0"
#15
1"
#20
0"
#25
1"
#30
0"
#35
1"
#40
0"
#45
1"
#50
0"
#55
1"
#60
0"
#65
1"
#70
0"
#75
1"
#80
0"
#85
1"
#90
0"
#95
1"
#100
0"
1#
#105
b1 !
b1 1
b100 2
b1 3
1"
#110
0"
#115
b1 0
b11 !
b11 1
1"
#120
0"
#125
b10 0
b111 !
b111 1
1"
#130
0"
#135
b11 0
b1111 !
b1111 1
1"
#140
0"
#145
b100 0
b11111 !
b11111 1
1"
#150
0"
0#
#155
b101 0
b111111 !
b111111 1
1"
#160
0"
#165
b11111 !
b11111 1
b0 0
b10 3
1"
#170
0"
#175
b1 0
b1111 !
b1111 1
1"
#180
0"
#185
b10 0
b111 !
b111 1
1"
#190
0"
#195
b11 0
b11 !
b11 1
1"
#200
0"
#205
b100 0
b1 !
b1 1
1"
#210
0"
#215
b101 0
b0 !
b0 1
1"
#220
0"
#225
b1 !
b1 1
b0 0
b1010 3
1"
#230
0"
#235
b1 0
b11 !
b11 1
1"
#240
0"
#245
b10 0
b111 !
b111 1
1"
#250
0"
#255
b11 0
b1111 !
b1111 1
1"
#260
0"
#265
b100 0
b11111 !
b11111 1
1"
#270
0"
#275
b101 0
b111111 !
b111111 1
1"
#280
0"
#285
b1111111 !
b1111111 1
b11 2
b0 0
b11 3
1"
#290
0"
#295
b1 0
b11111111 !
b11111111 1
1"
#300
0"
#305
b10 0
b111111111 !
b111111111 1
1"
#310
0"
#315
b11 0
b1111111111 !
b1111111111 1
1"
#320
0"
#325
b100 0
b11111111111 !
b11111111111 1
1"
#330
0"
#335
b1111111111 !
b1111111111 1
b100 2
b0 0
b101 3
1"
#340
0"
#345
b1 0
b111111111 !
b111111111 1
1"
#350
0"
#355
b10 0
b11111111 !
b11111111 1
1"
#360
0"
#365
b11 0
b1111111 !
b1111111 1
1"
#370
0"
#375
b100 0
b111111 !
b111111 1
1"
#380
0"
#385
b101 0
b11111 !
b11111 1
1"
#390
0"
#395
b111111 !
b111111 1
b0 2
b0 0
b110 3
1"
#400
0"
#405
b1 0
b1111111 !
b1111111 1
1"
#410
0"
#415
b11111111 !
b11111111 1
b11 2
b0 0
b1001 3
1"
#420
0"
#425
b1 0
b111111111 !
b111111111 1
1"
#430
0"
#435
b10 0
b1111111111 !
b1111111111 1
1"
#440
0"
#445
b11 0
b11111111111 !
b11111111111 1
1"
#450
0"
#455
b100 0
b111111111111 !
b111111111111 1
1"
#460
0"
#465
b1111111111111 !
b1111111111111 1
b10 2
b0 0
b1000 3
1"
#470
0"
#475
b1 0
b11111111111111 !
b11111111111111 1
1"
#480
0"
#485
b10 0
b111111111111111 !
b111111111111111 1
1"
#490
0"
#495
b11 0
b1111111111111111 !
b1111111111111111 1
1"
#500
0"
#505
b111111111111111 !
b111111111111111 1
b1111 2
b0 0
b0 3
1"
#510
0"
#515
b1 0
b11111111111111 !
b11111111111111 1
1"
#520
0"
#525
b10 0
b1111111111111 !
b1111111111111 1
1"
#530
0"
#535
b11 0
b111111111111 !
b111111111111 1
1"
#540
0"
#545
b100 0
b11111111111 !
b11111111111 1
1"
#550
0"
#555
b101 0
b1111111111 !
b1111111111 1
1"
#560
0"
#565
b110 0
b111111111 !
b111111111 1
1"
#570
0"
#575
b111 0
b11111111 !
b11111111 1
1"
#580
0"
#585
b1000 0
b1111111 !
b1111111 1
1"
#590
0"
#595
b1001 0
b111111 !
b111111 1
1"
#600
0"
1#
#605
b1010 0
b11111 !
b11111 1
1"
#610
0"
#615
b1011 0
b1111 !
b1111 1
1"
#620
0"
#625
b1100 0
b111 !
b111 1
1"
#630
0"
#635
b1101 0
b11 !
b11 1
1"
#640
0"
#645
b1110 0
b1 !
b1 1
1"
#650
0"
#655
b1111 0
b0 !
b0 1
1"
#660
0"
#665
b1 !
b1 1
b100 2
b0 0
b1 3
1"
#670
0"
#675
b1 0
b11 !
b11 1
1"
#680
0"
#685
b10 0
b111 !
b111 1
1"
#690
0"
#695
b11 0
b1111 !
b1111 1
1"
#700
0"
#705
b100 0
b11111 !
b11111 1
1"
#710
0"
#715
b101 0
b111111 !
b111111 1
1"
#720
0"
#725
b11111 !
b11111 1
b0 0
b10 3
1"
#730
0"
#735
b1 0
b1111 !
b1111 1
1"
#740
0"
#745
b10 0
b111 !
b111 1
1"
#750
0"
#755
b11 0
b11 !
b11 1
1"
#760
0"
#765
b100 0
b1 !
b1 1
1"
#770
0"
#775
b101 0
b0 !
b0 1
1"
#780
0"
#785
b1 !
b1 1
b0 0
b1010 3
1"
#790
0"
#795
b1 0
b11 !
b11 1
1"
#800
0"
#805
b10 0
b111 !
b111 1
1"
#810
0"
#815
b11 0
b1111 !
b1111 1
1"
#820
0"
#825
b100 0
b11111 !
b11111 1
1"
#830
0"
#835
b101 0
b111111 !
b111111 1
1"
#840
0"
#845
b11111 !
b11111 1
b0 0
b10 3
1"
#850
0"
#855
b1 0
b1111 !
b1111 1
1"
#860
0"
#865
b10 0
b111 !
b111 1
1"
#870
0"
#875
b11 0
b11 !
b11 1
1"
#880
0"
#885
b100 0
b1 !
b1 1
1"
#890
0"
#895
b101 0
b0 !
b0 1
1"
#900
0"
#905
b1 !
b1 1
b0 0
b1010 3
1"
#910
0"
#915
b1 0
b11 !
b11 1
1"
#920
0"
#925
b10 0
b111 !
b111 1
1"
#930
0"
#935
b11 0
b1111 !
b1111 1
1"
#940
0"
#945
b100 0
b11111 !
b11111 1
1"
#950
0"
#955
b101 0
b111111 !
b111111 1
1"
#960
0"
#965
b11111 !
b11111 1
b0 0
b10 3
1"
#970
0"
#975
b1 0
b1111 !
b1111 1
1"
#980
0"
#985
b10 0
b111 !
b111 1
1"
#990
0"
#995
b11 0
b11 !
b11 1
1"
#1000
0"
0#
#1005
b100 0
b1 !
b1 1
1"
#1010
0"
#1015
b101 0
b0 !
b0 1
1"
#1020
0"
#1025
b1 !
b1 1
b0 0
b1010 3
1"
#1030
0"
#1035
b1 0
b11 !
b11 1
1"
#1040
0"
#1045
b10 0
b111 !
b111 1
1"
#1050
0"
1#
#1055
b11 0
b1111 !
b1111 1
1"
#1060
0"
#1065
b100 0
b11111 !
b11111 1
1"
#1070
0"
#1075
b101 0
b111111 !
b111111 1
1"
#1080
0"
#1085
b11111 !
b11111 1
b0 0
b10 3
1"
#1090
0"
#1095
b1 0
b1111 !
b1111 1
1"
#1100
0"
#1105
b10 0
b111 !
b111 1
1"
#1110
0"
#1115
b11 0
b11 !
b11 1
1"
#1120
0"
#1125
b100 0
b1 !
b1 1
1"
#1130
0"
#1135
b101 0
b0 !
b0 1
1"
#1140
0"
#1145
b1 !
b1 1
b0 0
b1010 3
1"
#1150
0"
#1155
b1 0
b11 !
b11 1
1"
#1160
0"
#1165
b10 0
b111 !
b111 1
1"
#1170
0"
#1175
b11 0
b1111 !
b1111 1
1"
#1180
0"
#1185
b100 0
b11111 !
b11111 1
1"
#1190
0"
#1195
b101 0
b111111 !
b111111 1
1"
#1200
0"
#1205
b11111 !
b11111 1
b0 0
b10 3
1"
#1210
0"
#1215
b1 0
b1111 !
b1111 1
1"
#1220
0"
#1225
b10 0
b111 !
b111 1
1"
#1230
0"
#1235
b11 0
b11 !
b11 1
1"
#1240
0"
#1245
b100 0
b1 !
b1 1
1"
#1250
0"
#1255
b101 0
b0 !
b0 1
1"
#1260
0"
#1265
b1 !
b1 1
b0 0
b1010 3
1"
#1270
0"
#1275
b1 0
b11 !
b11 1
1"
#1280
0"
#1285
b10 0
b111 !
b111 1
1"
#1290
0"
#1295
b11 0
b1111 !
b1111 1
1"
#1300
0"
0#
#1305
b100 0
b11111 !
b11111 1
1"
#1310
0"
#1315
b101 0
b111111 !
b111111 1
1"
#1320
0"
#1325
b1111111 !
b1111111 1
b11 2
b0 0
b11 3
1"
#1330
0"
#1335
b1 0
b11111111 !
b11111111 1
1"
#1340
0"
#1345
b10 0
b111111111 !
b111111111 1
1"
#1350
0"
#1355
b11 0
b1111111111 !
b1111111111 1
1"
#1360
0"
#1365
b100 0
b11111111111 !
b11111111111 1
1"
#1370
0"
#1375
b1111111111 !
b1111111111 1
b100 2
b0 0
b101 3
1"
#1380
0"
#1385
b1 0
b111111111 !
b111111111 1
1"
#1390
0"
#1395
b10 0
b11111111 !
b11111111 1
1"
#1400
0"
1#
#1405
b11 0
b1111111 !
b1111111 1
1"
#1410
0"
#1415
b100 0
b111111 !
b111111 1
1"
#1420
0"
#1425
b101 0
b11111 !
b11111 1
1"
#1430
0"
#1435
b111111 !
b111111 1
b0 2
b0 0
b110 3
1"
#1440
0"
#1445
b1 0
b1111111 !
b1111111 1
1"
#1450
0"
#1455
b111111 !
b111111 1
b0 0
b111 3
1"
#1460
0"
#1465
b1 0
b11111 !
b11111 1
1"
#1470
0"
#1475
b1 2
b0 0
b110 3
1"
#1480
0"
#1485
b1 0
b111111 !
b111111 1
1"
#1490
0"
#1495
b10 0
b1111111 !
b1111111 1
1"
#1500
0"
0#
#1505
b11111111 !
b11111111 1
b11 2
b0 0
b1001 3
1"
#1510
0"
#1515
b1 0
b111111111 !
b111111111 1
1"
#1520
0"
#1525
b10 0
b1111111111 !
b1111111111 1
1"
#1530
0"
#1535
b11 0
b11111111111 !
b11111111111 1
1"
#1540
0"
#1545
b100 0
b111111111111 !
b111111111111 1
1"
#1550
0"
#1555
b1111111111111 !
b1111111111111 1
b10 2
b0 0
b1000 3
1"
#1560
0"
#1565
b1 0
b11111111111111 !
b11111111111111 1
1"
#1570
0"
#1575
b10 0
b111111111111111 !
b111111111111111 1
1"
#1580
0"
#1585
b11 0
b1111111111111111 !
b1111111111111111 1
1"
#1590
0"
#1595
b111111111111111 !
b111111111111111 1
b1111 2
b0 0
b0 3
1"
#1600
0"
1#
#1605
b1 0
b11111111111111 !
b11111111111111 1
1"
#1610
0"
#1615
b10 0
b1111111111111 !
b1111111111111 1
1"
#1620
0"
#1625
b11 0
b111111111111 !
b111111111111 1
1"
#1630
0"
#1635
b100 0
b11111111111 !
b11111111111 1
1"
#1640
0"
#1645
b101 0
b1111111111 !
b1111111111 1
1"
#1650
0"
#1655
b110 0
b111111111 !
b111111111 1
1"
#1660
0"
#1665
b111 0
b11111111 !
b11111111 1
1"
#1670
0"
#1675
b1000 0
b1111111 !
b1111111 1
1"
#1680
0"
#1685
b1001 0
b111111 !
b111111 1
1"
#1690
0"
#1695
b1010 0
b11111 !
b11111 1
1"
#1700
0"
0#
#1705
b1011 0
b1111 !
b1111 1
1"
#1710
0"
#1715
b1100 0
b111 !
b111 1
1"
#1720
0"
#1725
b1101 0
b11 !
b11 1
1"
#1730
0"
#1735
b1110 0
b1 !
b1 1
1"
#1740
0"
#1745
b1111 0
b0 !
b0 1
1"
#1750
0"
#1755
1"
#1760
0"
#1765
1"
#1770
0"
#1775
1"
#1780
0"
#1785
1"
#1790
0"
#1795
1"
#1800
0"
#1805
1"
#1810
0"
#1815
1"
#1820
0"
#1825
1"
#1830
0"
#1835
1"
#1840
0"
#1845
1"
#1850
0"
#1855
1"
#1860
0"
#1865
1"
#1870
0"
#1875
1"
#1880
0"
#1885
1"
#1890
0"
#1895
1"
#1900
0"
1#
#1905
b1 !
b1 1
b100 2
b0 0
b1 3
1"
#1910
0"
#1915
b1 0
b11 !
b11 1
1"
#1920
0"
#1925
b10 0
b111 !
b111 1
1"
#1930
0"
#1935
b11 0
b1111 !
b1111 1
1"
#1940
0"
#1945
b100 0
b11111 !
b11111 1
1"
#1950
0"
#1955
b101 0
b111111 !
b111111 1
1"
#1960
0"
#1965
b11111 !
b11111 1
b0 0
b10 3
1"
#1970
0"
#1975
b1 0
b1111 !
b1111 1
1"
#1980
0"
#1985
b10 0
b111 !
b111 1
1"
#1990
0"
#1995
b11 0
b11 !
b11 1
1"
#2000
0"
0#
#2005
b100 0
b1 !
b1 1
1"
#2010
0"
#2015
b101 0
b0 !
b0 1
1"
#2020
0"
#2025
b1 !
b1 1
b0 0
b1010 3
1"
#2030
0"
#2035
b1 0
b11 !
b11 1
1"
#2040
0"
#2045
b10 0
b111 !
b111 1
1"
#2050
0"
1#
#2055
b11 0
b1111 !
b1111 1
1"
#2060
0"
#2065
b100 0
b11111 !
b11111 1
1"
#2070
0"
#2075
b101 0
b111111 !
b111111 1
1"
#2080
0"
#2085
b11111 !
b11111 1
b0 0
b10 3
1"
#2090
0"
#2095
b1 0
b1111 !
b1111 1
1"
#2100
0"
#2105
b10 0
b111 !
b111 1
1"
#2110
0"
#2115
b11 0
b11 !
b11 1
1"
#2120
0"
#2125
b100 0
b1 !
b1 1
1"
#2130
0"
#2135
b101 0
b0 !
b0 1
1"
#2140
0"
#2145
b1 !
b1 1
b0 0
b1010 3
1"
#2150
0"
0#
#2155
b1 0
b11 !
b11 1
1"
#2160
0"
#2165
b10 0
b111 !
b111 1
1"
#2170
0"
#2175
b11 0
b1111 !
b1111 1
1"
#2180
0"
#2185
b100 0
b11111 !
b11111 1
1"
#2190
0"
#2195
b101 0
b111111 !
b111111 1
1"
#2200
0"
#2205
b1111111 !
b1111111 1
b11 2
b0 0
b11 3
1"
#2210
0"
#2215
b1 0
b11111111 !
b11111111 1
1"
#2220
0"
#2225
b10 0
b111111111 !
b111111111 1
1"
#2230
0"
#2235
b11 0
b1111111111 !
b1111111111 1
1"
#2240
0"
#2245
b100 0
b11111111111 !
b11111111111 1
1"
#2250
0"
#2255
b1111111111 !
b1111111111 1
b100 2
b0 0
b101 3
1"
#2260
0"
#2265
b1 0
b111111111 !
b111111111 1
1"
#2270
0"
#2275
b10 0
b11111111 !
b11111111 1
1"
#2280
0"
#2285
b11 0
b1111111 !
b1111111 1
1"
#2290
0"
#2295
b100 0
b111111 !
b111111 1
1"
#2300
0"
#2305
b101 0
b11111 !
b11111 1
1"
#2310
0"
#2315
b111111 !
b111111 1
b0 2
b0 0
b110 3
1"
#2320
0"
#2325
b1 0
b1111111 !
b1111111 1
1"
#2330
0"
#2335
b11111111 !
b11111111 1
b11 2
b0 0
b1001 3
1"
#2340
0"
#2345
b1 0
b111111111 !
b111111111 1
1"
#2350
0"
#2355
b10 0
b1111111111 !
b1111111111 1
1"
#2360
0"
#2365
b11 0
b11111111111 !
b11111111111 1
1"
#2370
0"
#2375
b100 0
b111111111111 !
b111111111111 1
1"
#2380
0"
#2385
b1111111111111 !
b1111111111111 1
b10 2
b0 0
b1000 3
1"
#2390
0"
#2395
b1 0
b11111111111111 !
b11111111111111 1
1"
#2400
0"
#2405
b10 0
b111111111111111 !
b111111111111111 1
1"
#2410
0"
#2415
b11 0
b1111111111111111 !
b1111111111111111 1
1"
#2420
0"
#2425
b111111111111111 !
b111111111111111 1
b1111 2
b0 0
b0 3
1"
#2430
0"
#2435
b1 0
b11111111111111 !
b11111111111111 1
1"
#2440
0"
#2445
b10 0
b1111111111111 !
b1111111111111 1
1"
#2450
0"
1#
#2455
b11 0
b111111111111 !
b111111111111 1
1"
#2460
0"
#2465
b100 0
b11111111111 !
b11111111111 1
1"
#2470
0"
#2475
b101 0
b1111111111 !
b1111111111 1
1"
#2480
0"
#2485
b110 0
b111111111 !
b111111111 1
1"
#2490
0"
0#
#2495
b111 0
b11111111 !
b11111111 1
1"
#2500
0"
#2505
b1000 0
b1111111 !
b1111111 1
1"
#2510
0"
#2515
b1001 0
b111111 !
b111111 1
1"
#2520
0"
#2525
b1010 0
b11111 !
b11111 1
1"
#2530
0"
#2535
b1011 0
b1111 !
b1111 1
1"
#2540
0"
#2545
b1100 0
b111 !
b111 1
1"
#2550
0"
#2555
b1101 0
b11 !
b11 1
1"
#2560
0"
#2565
b1110 0
b1 !
b1 1
1"
#2570
0"
#2575
b1111 0
b0 !
b0 1
1"
