lab_1/bound_flasher.v
module bound_flasher(clk, flick, reset, lamp);

input wire clk;
input wire flick;
input wire reset;

output reg [15:0] lamp;

localparam s0 = 4'b0000;
localparam s1 = 4'b0001;
localparam s2 = 4'b0010;
localparam s3 = 4'b0011;
localparam s4 = 4'b0100;    
localparam s5 = 4'b0101;
localparam s6 = 4'b0110;
localparam s7 = 4'b0111;
localparam s8 = 4'b1000;
localparam s9 = 4'b1001;
localparam s10 = 4'b1010;

reg [3:0] state = 4'b0000;
reg [3:0] bit_shifted = 4'b0000;
reg [3:0] n_bit_shift = 4'b0000;

always @(posedge reset) begin
    state <= s0;
end

always @(posedge clk) begin
    // state 0
    if (state == s0) begin
        lamp <= 0;
        if (flick) begin
            state <= s1;
            bit_shifted <= 0;
            n_bit_shift <= 5;
        end
    end
    // state 1
    else if (state == s1) begin
        if (bit_shifted <= n_bit_shift)begin
            lamp <= (lamp << 1) + 1;
            bit_shifted <= bit_shifted + 1;
        end else begin
            state <= s2;
            bit_shifted = 0;
            n_bit_shift = 5;
        end
    end
    // state 2
    else if (state == s2) begin
        if (bit_shifted <= n_bit_shift)begin
            lamp = lamp >> 1;
            bit_shifted = bit_shifted + 1;
        end else begin
            state = s10;
            bit_shifted = 0;
            n_bit_shift = 5;
        end
    end
    // state 3
    else if (state == s3) begin
        if (bit_shifted <= n_bit_shift)begin
            lamp = (lamp << 1) + 1;
            bit_shifted = bit_shifted + 1;
        end else begin
            state = flick ? s4 : s5;
            bit_shifted = 0;
            n_bit_shift = (state == s4) ? 10 : 5;
        end
    end
    // state 4
    else if (state == s4) begin
        if (bit_shifted <= n_bit_shift)begin
            lamp = lamp >> 1;
            bit_shifted = bit_shifted + 1;
        end else begin
            state = s4;
        end
    end
    // state 5
    else if (state == s5) begin
        if (bit_shifted <= n_bit_shift) begin
            lamp = lamp >> 1;
            bit_shifted = bit_shifted + 1;
        end else begin
            state = s6;
            bit_shifted = 0;
            n_bit_shift = 0;
        end
    end
    // state 6
    else if (state == s6) begin
        if (bit_shifted <= n_bit_shift) begin
            lamp = (lamp << 1) + 1;
            bit_shifted = bit_shifted + 1;
        end else begin
            state = flick ? s7 : s9;
            bit_shifted = 0;
            n_bit_shift = (state == s7) ? 1 : 4;
        end
    end
    // state 7
    else if (state == s7) begin
        if (bit_shifted <= n_bit_shift) begin
            lamp = lamp >> 1;
            bit_shifted = bit_shifted + 1;
        end else begin
            state = 6;
            bit_shifted = 0;
            n_bit_shift = 1;
        end
    end
    // state 8
    else if (state == s8) begin
        if (bit_shifted <= n_bit_shift) begin
            lamp = (lamp << 1) + 1;
            bit_shifted = bit_shifted + 1;
        end else begin
            state = s0;
        end
    end
    // state 9
    else if (state == s9) begin
        if (bit_shifted <= n_bit_shift) begin
            lamp = (lamp << 1) + 1;
            bit_shifted = bit_shifted + 1;
        end else begin
            state = flick ? s5 : s8;
            bit_shifted = 0;
            n_bit_shift = 5;
        end
    end
    // state 10
    else if (state == s10) begin
        if (bit_shifted <= n_bit_shift) begin
            lamp = (lamp << 1) + 1;
            bit_shifted = bit_shifted + 1;
        end else begin
            state = flick ? s2 : s3;
            bit_shifted = 0;
            n_bit_shift = (state == s3) ? 4 : 5;
        end
    end
end

endmodule

lab_1/tb.v
module bound_flasher_tb;
    reg clk;
    reg flick;
    reg reset;
    wire [15:0] lamp;

    bound_flasher uut
    (
        .clk (clk),
        .flick (flick),
        .reset(reset),
        .lamp (lamp)
    );

    initial begin
        $dumpfile("bound_flash_tb.vcd");
        $dumpvars(0, bound_flasher_tb);
    end

    initial begin
        clk = 0;
        reset = 1;
    end

    always #10 clk = ~clk;

    initial begin
        #10 
        reset = 0;
        #10
        assign flick = 1;
        #10
        repeat(20) @ (clk);
        #10
        assign flick = 0;
        #10
        repeat(90) @ (clk);
        #10
        assign flick = 1;
        #10
        repeat(90) @ (clk);
        #10
        assign reset = 1;
        #10
        assign reset = 0;
        repeat(90) @ (clk);
        $finish;
    end
endmodule

lab_1/bound_flash_tb.vcd
$date
	Sat Feb 18 16:22:15 2023
$end
$version
	Icarus Verilog
$end
$timescale
	1s
$end
$scope module bound_flasher_tb $end
$var wire 16 ! lamp [15:0] $end
$var reg 1 " clk $end
$var reg 1 # flick $end
$var reg 1 $ reset $end
$scope module uut $end
$var wire 1 " clk $end
$var wire 1 # flick $end
$var wire 1 $ reset $end
$var parameter 4 % s0 $end
$var parameter 4 & s1 $end
$var parameter 4 ' s10 $end
$var parameter 4 ( s2 $end
$var parameter 4 ) s3 $end
$var parameter 4 * s4 $end
$var parameter 4 + s5 $end
$var parameter 4 , s6 $end
$var parameter 4 - s7 $end
$var parameter 4 . s8 $end
$var parameter 4 / s9 $end
$var reg 4 0 bit_shifted [3:0] $end
$var reg 16 1 lamp [15:0] $end
$var reg 4 2 n_bit_shift [3:0] $end
$var reg 4 3 state [3:0] $end
$upscope $end
$upscope $end
$enddefinitions $end
$comment Show the parameter values. $end
$dumpall
b1001 /
b1000 .
b111 -
b110 ,
b101 +
b100 *
b11 )
b10 (
b1010 '
b1 &
b0 %
$end
#0
$dumpvars
b0 3
b0 2
bx 1
b0 0
1$
x#
0"
bx !
$end
#10
b0 !
b0 1
0$
1"
#20
1#
0"
#30
b101 2
b1 3
1"
#40
0"
#50
b1 0
b1 !
b1 1
1"
#60
0"
#70
b10 0
b11 !
b11 1
1"
#80
0"
#90
b11 0
b111 !
b111 1
1"
#100
0"
#110
b100 0
b1111 !
b1111 1
1"
#120
0"
#130
b101 0
b11111 !
b11111 1
1"
#140
0"
#150
b110 0
b111111 !
b111111 1
1"
#160
0"
#170
b10 3
b0 0
1"
#180
0"
#190
b1 0
b11111 !
b11111 1
1"
#200
0"
#210
b10 0
b1111 !
b1111 1
1"
#220
0"
#230
b11 0
b111 !
b111 1
1"
#240
0#
0"
#250
b100 0
b11 !
b11 1
1"
#260
0"
#270
b101 0
b1 !
b1 1
1"
#280
0"
#290
b110 0
b0 !
b0 1
1"
#300
0"
#310
b0 0
b1010 3
1"
#320
0"
#330
b1 0
b1 !
b1 1
1"
#340
0"
#350
b10 0
b11 !
b11 1
1"
#360
0"
#370
b11 0
b111 !
b111 1
1"
#380
0"
#390
b100 0
b1111 !
b1111 1
1"
#400
0"
#410
b101 0
b11111 !
b11111 1
1"
#420
0"
#430
b110 0
b111111 !
b111111 1
1"
#440
0"
#450
b100 2
b0 0
b11 3
1"
#460
0"
#470
b1 0
b1111111 !
b1111111 1
1"
#480
0"
#490
b10 0
b11111111 !
b11111111 1
1"
#500
0"
#510
b11 0
b111111111 !
b111111111 1
1"
#520
0"
#530
b100 0
b1111111111 !
b1111111111 1
1"
#540
0"
#550
b101 0
b11111111111 !
b11111111111 1
1"
#560
0"
#570
b101 2
b0 0
b101 3
1"
#580
0"
#590
b1 0
b1111111111 !
b1111111111 1
1"
#600
0"
#610
b10 0
b111111111 !
b111111111 1
1"
#620
0"
#630
b11 0
b11111111 !
b11111111 1
1"
#640
0"
#650
b100 0
b1111111 !
b1111111 1
1"
#660
0"
#670
b101 0
b111111 !
b111111 1
1"
#680
0"
#690
b110 0
b11111 !
b11111 1
1"
#700
0"
#710
b0 2
b0 0
b110 3
1"
#720
0"
#730
b1 0
b111111 !
b111111 1
1"
#740
0"
#750
b100 2
b0 0
b1001 3
1"
#760
0"
#770
b1 0
b1111111 !
b1111111 1
1"
#780
0"
#790
b10 0
b11111111 !
b11111111 1
1"
#800
0"
#810
b11 0
b111111111 !
b111111111 1
1"
#820
0"
#830
b100 0
b1111111111 !
b1111111111 1
1"
#840
0"
#850
b101 0
b11111111111 !
b11111111111 1
1"
#860
0"
#870
b101 2
b0 0
b1000 3
1"
#880
0"
#890
b1 0
b111111111111 !
b111111111111 1
1"
#900
0"
#910
b10 0
b1111111111111 !
b1111111111111 1
1"
#920
0"
#930
b11 0
b11111111111111 !
b11111111111111 1
1"
#940
0"
#950
b100 0
b111111111111111 !
b111111111111111 1
1"
#960
0"
#970
b101 0
b1111111111111111 !
b1111111111111111 1
1"
#980
0"
#990
b110 0
1"
#1000
0"
#1010
b0 3
1"
#1020
0"
#1030
b0 !
b0 1
1"
#1040
0"
#1050
1"
#1060
0"
#1070
1"
#1080
0"
#1090
1"
#1100
0"
#1110
1"
#1120
0"
#1130
1"
#1140
0"
#1150
1"
#1160
1#
0"
#1170
b0 0
b1 3
1"
#1180
0"
#1190
b1 0
b1 !
b1 1
1"
#1200
0"
#1210
b10 0
b11 !
b11 1
1"
#1220
0"
#1230
b11 0
b111 !
b111 1
1"
#1240
0"
#1250
b100 0
b1111 !
b1111 1
1"
#1260
0"
#1270
b101 0
b11111 !
b11111 1
1"
#1280
0"
#1290
b110 0
b111111 !
b111111 1
1"
#1300
0"
#1310
b10 3
b0 0
1"
#1320
0"
#1330
b1 0
b11111 !
b11111 1
1"
#1340
0"
#1350
b10 0
b1111 !
b1111 1
1"
#1360
0"
#1370
b11 0
b111 !
b111 1
1"
#1380
0"
#1390
b100 0
b11 !
b11 1
1"
#1400
0"
#1410
b101 0
b1 !
b1 1
1"
#1420
0"
#1430
b110 0
b0 !
b0 1
1"
#1440
0"
#1450
b0 0
b1010 3
1"
#1460
0"
#1470
b1 0
b1 !
b1 1
1"
#1480
0"
#1490
b10 0
b11 !
b11 1
1"
#1500
0"
#1510
b11 0
b111 !
b111 1
1"
#1520
0"
#1530
b100 0
b1111 !
b1111 1
1"
#1540
0"
#1550
b101 0
b11111 !
b11111 1
1"
#1560
0"
#1570
b110 0
b111111 !
b111111 1
1"
#1580
0"
#1590
b0 0
b10 3
1"
#1600
0"
#1610
b1 0
b11111 !
b11111 1
1"
#1620
0"
#1630
b10 0
b1111 !
b1111 1
1"
#1640
0"
#1650
b11 0
b111 !
b111 1
1"
#1660
0"
#1670
b100 0
b11 !
b11 1
1"
#1680
0"
#1690
b101 0
b1 !
b1 1
1"
#1700
0"
#1710
b110 0
b0 !
b0 1
1"
#1720
0"
#1730
b0 0
b1010 3
1"
#1740
0"
#1750
b1 0
b1 !
b1 1
1"
#1760
0"
#1770
b10 0
b11 !
b11 1
1"
#1780
0"
#1790
b11 0
b111 !
b111 1
1"
#1800
0"
#1810
b100 0
b1111 !
b1111 1
1"
#1820
0"
#1830
b101 0
b11111 !
b11111 1
1"
#1840
0"
#1850
b110 0
b111111 !
b111111 1
1"
#1860
0"
#1870
b0 0
b10 3
1"
#1880
0"
#1890
b1 0
b11111 !
b11111 1
1"
#1900
0"
#1910
b10 0
b1111 !
b1111 1
1"
#1920
0"
#1930
b11 0
b111 !
b111 1
1"
#1940
0"
#1950
b100 0
b11 !
b11 1
1"
#1960
0"
#1970
b101 0
b1 !
b1 1
1"
#1980
0"
#1990
b110 0
b0 !
b0 1
1"
#2000
0"
#2010
b0 0
b1010 3
1"
#2020
0"
#2030
b1 0
b1 !
b1 1
1"
#2040
0"
#2050
b10 0
b11 !
b11 1
1"
#2060
0"
#2070
b11 0
b111 !
b111 1
1"
#2080
b0 3
1$
0"
#2090
b0 0
b1 3
b0 !
b0 1
0$
1"
#2100
0"
#2110
b1 0
b1 !
b1 1
1"
#2120
0"
#2130
b10 0
b11 !
b11 1
1"
#2140
0"
#2150
b11 0
b111 !
b111 1
1"
#2160
0"
#2170
b100 0
b1111 !
b1111 1
1"
#2180
0"
#2190
b101 0
b11111 !
b11111 1
1"
#2200
0"
#2210
b110 0
b111111 !
b111111 1
1"
#2220
0"
#2230
b10 3
b0 0
1"
#2240
0"
#2250
b1 0
b11111 !
b11111 1
1"
#2260
0"
#2270
b10 0
b1111 !
b1111 1
1"
#2280
0"
#2290
b11 0
b111 !
b111 1
1"
#2300
0"
#2310
b100 0
b11 !
b11 1
1"
#2320
0"
#2330
b101 0
b1 !
b1 1
1"
#2340
0"
#2350
b110 0
b0 !
b0 1
1"
#2360
0"
#2370
b0 0
b1010 3
1"
#2380
0"
#2390
b1 0
b1 !
b1 1
1"
#2400
0"
#2410
b10 0
b11 !
b11 1
1"
#2420
0"
#2430
b11 0
b111 !
b111 1
1"
#2440
0"
#2450
b100 0
b1111 !
b1111 1
1"
#2460
0"
#2470
b101 0
b11111 !
b11111 1
1"
#2480
0"
#2490
b110 0
b111111 !
b111111 1
1"
#2500
0"
#2510
b0 0
b10 3
1"
#2520
0"
#2530
b1 0
b11111 !
b11111 1
1"
#2540
0"
#2550
b10 0
b1111 !
b1111 1
1"
#2560
0"
#2570
b11 0
b111 !
b111 1
1"
#2580
0"
#2590
b100 0
b11 !
b11 1
1"
#2600
0"
#2610
b101 0
b1 !
b1 1
1"
#2620
0"
#2630
b110 0
b0 !
b0 1
1"
#2640
0"
#2650
b0 0
b1010 3
1"
#2660
0"
#2670
b1 0
b1 !
b1 1
1"
#2680
0"
#2690
b10 0
b11 !
b11 1
1"
#2700
0"
#2710
b11 0
b111 !
b111 1
1"
#2720
0"
#2730
b100 0
b1111 !
b1111 1
1"
#2740
0"
#2750
b101 0
b11111 !
b11111 1
1"
#2760
0"
#2770
b110 0
b111111 !
b111111 1
1"
#2780
0"
#2790
b0 0
b10 3
1"
#2800
0"
#2810
b1 0
b11111 !
b11111 1
1"
#2820
0"
#2830
b10 0
b1111 !
b1111 1
1"
#2840
0"
#2850
b11 0
b111 !
b111 1
1"
#2860
0"
#2870
b100 0
b11 !
b11 1
1"
#2880
0"
#2890
b101 0
b1 !
b1 1
1"
#2900
0"
#2910
b110 0
b0 !
b0 1
1"
#2920
0"
#2930
b0 0
b1010 3
1"
#2940
0"
#2950
b1 0
b1 !
b1 1
1"
#2960
0"
#2970
b10 0
b11 !
b11 1
1"
#2980
0"
#2990
b11 0
b111 !
b111 1
1"
